progimage/__init__.py
progimage/image.py
progimage-0.0.9.dist-info/LICENCE
progimage-0.0.9.dist-info/METADATA
progimage-0.0.9.dist-info/WHEEL
progimage-0.0.9.dist-info/top_level.txt
progimage-0.0.9.dist-info/RECORD
