Metadata-Version: 2.1
Name: progimage
Version: 0.0.9
Summary: Python client library for the ProgImage API
Home-page: https://github.com/Nasko29/progimage-python
Author: Nasko Grozdanov
Author-email: antonasko@gmail.com
License: UNKNOWN
Platform: UNKNOWN
Classifier: Programming Language :: Python :: 3
Classifier: License :: OSI Approved :: MIT License
Classifier: Operating System :: OS Independent
